string_obfuscator/__init__.py
string_obfuscator/obfuscate.py
string_obfuscator-1.0.0.dist-info/LICENSE
string_obfuscator-1.0.0.dist-info/METADATA
string_obfuscator-1.0.0.dist-info/WHEEL
string_obfuscator-1.0.0.dist-info/top_level.txt
string_obfuscator-1.0.0.dist-info/RECORD
