Metadata-Version: 2.1
Name: string-obfuscator
Version: 1.0.0
Summary: A simple string obfuscator for obfuscating strings inside nested dicts.
Home-page: https://github.com/eduardolm/string_obfuscator
Author: Eduardo Lodi Marzano
Author-email: lodi001@uol.com.br
Project-URL: Bug Tracker, https://github.com/eduardolm/string_obfuscator/issues
Classifier: Programming Language :: Python :: 3
Classifier: License :: OSI Approved :: MIT License
Classifier: Operating System :: OS Independent
Requires-Python: >=3.6
License-File: LICENSE
